cubicweb_localperms/__init__.py
cubicweb_localperms/__pkginfo__.py
cubicweb_localperms/ccplugin.py
cubicweb_localperms/entities.py
cubicweb_localperms/hooks.py
cubicweb_localperms/schema.py
cubicweb_localperms/site_cubicweb.py
cubicweb_localperms/views.py
cubicweb_localperms/i18n/en.po
cubicweb_localperms/i18n/es.po
cubicweb_localperms/i18n/fr.po
cubicweb_localperms-1.1.0.dist-info/METADATA
cubicweb_localperms-1.1.0.dist-info/WHEEL
cubicweb_localperms-1.1.0.dist-info/entry_points.txt
cubicweb_localperms-1.1.0.dist-info/top_level.txt
cubicweb_localperms-1.1.0.dist-info/RECORD
